{"name":"Governify.io","tagline":"","body":"# Index\r\n\r\n## Main projects\r\n* [portal.governify.io](#)\r\n* [dashboard.governify.io](#)\r\n* [datastore.governify.io](#)\r\n* [conector.governify.io/trello](#)\r\n* [conector.governify.io/drive](#)\r\n\r\n## Showcases\r\n* [portal.governify.io/showcase/papamoscas](#)\r\n* [portal.governify.io/showcase/trello](#)\r\n* [portal.governify.io/showcase/drive](#)\r\n* [dashboard.governify.io/showcase/trello](#)\r\n* [dashboard.governify.io/showcase/papamoscas](#)","google":"","note":"Don't delete this file! It's used internally to help with page regeneration."}